LICENSE
README.md
setup.py
tf_ffcv/__init__.py
tf_ffcv.egg-info/PKG-INFO
tf_ffcv.egg-info/SOURCES.txt
tf_ffcv.egg-info/dependency_links.txt
tf_ffcv.egg-info/top_level.txt