Metadata-Version: 2.1
Name: tf-ffcv
Version: 0.0.2
Summary: Utilitaries to integrate tensorflow to FFCV
Home-page: UNKNOWN
Author: MadryLab
Author-email: leclerc@mit.edu
License: UNKNOWN
Platform: UNKNOWN
License-File: LICENSE
